limitify/__init__.py
limitify/helpers.py
limitify/sdk_core.py
limitify-0.1.1.dist-info/licenses/LICENSE
limitify-0.1.1.dist-info/METADATA
limitify-0.1.1.dist-info/WHEEL
limitify-0.1.1.dist-info/top_level.txt
limitify-0.1.1.dist-info/RECORD
