Metadata-Version: 2.4
Name: limitify
Version: 0.1.1
Summary: A simple api rate-limiting library with analytics support
Home-page: https://github.com/Mr-Aaryan/limitify
Author: Aryan KC
Author-email: kc.aryan3536@gmail.com.com
Classifier: Programming Language :: Python :: 3
Classifier: License :: OSI Approved :: MIT License
Classifier: Operating System :: OS Independent
Requires-Python: >=3.13.3
License-File: LICENSE
Requires-Dist: httpx
Requires-Dist: geoip2
Dynamic: author
Dynamic: author-email
Dynamic: classifier
Dynamic: description
Dynamic: description-content-type
Dynamic: home-page
Dynamic: license-file
Dynamic: requires-dist
Dynamic: requires-python
Dynamic: summary
